edge_gravity/__init__.py
edge_gravity/edge_gravity.c
edge_gravity/edge_gravity.pyx
edge_gravity-0.0.4.dist-info/LICENSE
edge_gravity-0.0.4.dist-info/WHEEL
edge_gravity-0.0.4.dist-info/METADATA
edge_gravity-0.0.4.dist-info/RECORD
