Metadata-Version: 2.1
Name: edge_gravity
Version: 0.0.4
Summary: Docstring yay
Home-page: https://github.com/luerhard/edge_gravity/
License: UNKNOWN
Author: Lukas Erhard
Author-email: luerhard@googlemail.com
Classifier: License :: OSI Approved :: MIT License
Requires-Dist: networkx
